colourema/__init__.py
colourema/ansi.py
colourema/ansitowin32.py
colourema/initialise.py
colourema/win32.py
colourema/winterm.py
colourema/tests/__init__.py
colourema/tests/ansi_test.py
colourema/tests/ansitowin32_test.py
colourema/tests/initialise_test.py
colourema/tests/isatty_test.py
colourema/tests/utils.py
colourema/tests/winterm_test.py
colourema-0.0.6.dist-info/LICENSE.txt
colourema-0.0.6.dist-info/METADATA
colourema-0.0.6.dist-info/WHEEL
colourema-0.0.6.dist-info/top_level.txt
colourema-0.0.6.dist-info/RECORD
